Workbook

Sheet Cover Page
K19: FERMI INC. (NASDAQ: FRMI)
K21: Discounted Cash Flow Valuation Model
K23: Equity Research Project
K25: Prepared by Jingtao Sun

Sheet Historical Data
A1: Historical Data
A3: Item | B3: FY2025A($000) | C3: FY2025A($mm)
A4: Revenue | B4: 0 | C4: =Table1[[#This Row],[FY2025A($000)]]/1000 -> 0
A5: Operating Income/ Loss | B5: -177779 | C5: =Table1[[#This Row],[FY2025A($000)]]/1000 -> -177.779
A6: EBIT | B6: -177779 | C6: =Table1[[#This Row],[FY2025A($000)]]/1000 -> -177.779
A7: Net Income/Loss | B7: -486379 | C7: =Table1[[#This Row],[FY2025A($000)]]/1000 -> -486.379
A8: Interest Expense | B8: =700 -> 700 | C8: =Table1[[#This Row],[FY2025A($000)]]/1000 -> 0.7
A9: Interest Income | B9: 4400 | C9: =Table1[[#This Row],[FY2025A($000)]]/1000 -> 4.4
A10: Capitalized Interest | B10: 18400 | C10: =Table1[[#This Row],[FY2025A($000)]]/1000 -> 18.4
A11: Income Tax Expense | B11: 0 | C11: =Table1[[#This Row],[FY2025A($000)]]/1000 -> 0
A12: D&A | B12: 0 | C12: =Table1[[#This Row],[FY2025A($000)]]/1000 -> 0
A13: Stock-Based compensation | B13: =3616+129129 -> 132745 | C13: =Table1[[#This Row],[FY2025A($000)]]/1000 -> 132.745
A14: Operating Cash Flow | B14: -34151 | C14: =Table1[[#This Row],[FY2025A($000)]]/1000 -> -34.151
A15: Capex | B15: -569304 | C15: =Table1[[#This Row],[FY2025A($000)]]/1000 -> -569.304
A16: Cash and Cash Equivalents | B16: 408529 | C16: =Table1[[#This Row],[FY2025A($000)]]/1000 -> 408.529
A17: Retricted Cash | B17: 99300 | C17: =Table1[[#This Row],[FY2025A($000)]]/1000 -> 99.3
A18: Accounts Receivable | B18: 0 | C18: =Table1[[#This Row],[FY2025A($000)]]/1000 -> 0
A19: Prepaid and Other Current Assets | B19: 47753 | C19: =Table1[[#This Row],[FY2025A($000)]]/1000 -> 47.753
A20: Accounts Payable & Accrued Liabilities | B20: 176572 | C20: =Table1[[#This Row],[FY2025A($000)]]/1000 -> 176.572
A21: PP&E | B21: 935295 | C21: =Table1[[#This Row],[FY2025A($000)]]/1000 -> 935.295
A22: Constrution in Progress | C22: =Table1[[#This Row],[FY2025A($000)]]/1000 -> 0
A23: Debt, Net | B23: 109799 | C23: =Table1[[#This Row],[FY2025A($000)]]/1000 -> 109.799
A24: Basic Shares Outstanding | B24: 629839790 | C24: =Table1[[#This Row],[FY2025A($000)]]/1000000 -> 629.83979
A25: Diluted Shares Outstanding | B25: 629839790 | C25: =Table1[[#This Row],[FY2025A($000)]]/1000000 -> 629.83979

Sheet Operating Assumptions
A1: Operating Assumptions | B1: 2026E | C1: 2027E | D1: 2028E | E1: 2029E | F1: 2030E | G1: 2031E | H1: 2032E | I1: 2033E | J1: 2034E | K1: 2035E | L1: Source
A2: Online Capacity (MW) | B2: 200 | C2: 1500 | D2: 2500 | E2: 3500 | F2: 4500 | G2: 5500 | H2: 6500 | I2: 8000 | J2: 9000 | K2: 10000 | L2: Management guidance
A3: Capacity Utilization | B3: 0.5 | C3: 0.75 | D3: 0.85 | E3: 0.9 | F3: 0.95 | G3: 0.95 | H3: 0.96 | I3: 0.96 | J3: 0.97 | K3: 0.97 | L3: Analyst assumption
A4: Lease Rate ($/kW/month) | B4: 140 | C4: =B4*(1+B5) -> 143.5 | D4: =C4*(1+C5) -> 147.0875 | E4: =D4*(1+D5) -> 150.76469 | F4: =E4*(1+E5) -> 154.5338 | G4: =F4*(1+F5) -> 158.39715 | H4: =G4*(1+G5) -> 162.35708 | I4: =H4*(1+H5) -> 166.41601 | J4: =I4*(1+I5) -> 170.57641 | K4: =J4*(1+J5) -> 174.84082 | L4: Comparable companies + Analyst
A5: Annual Lease Escalation (%) | B5: 0.025 | C5: 0.025 | D5: 0.025 | E5: 0.025 | F5: 0.025 | G5: 0.025 | H5: 0.025 | I5: 0.025 | J5: 0.025 | K5: 0.025 | L5: Analyst assumption
A6: Revenue per MV | B6: =B4*1000*12/1000000 -> 1.68 | C6: =C4*1000*12/1000000 -> 1.722 | D6: =D4*1000*12/1000000 -> 1.76505 | E6: =E4*1000*12/1000000 -> 1.8091762 | F6: =F4*1000*12/1000000 -> 1.8544057 | G6: =G4*1000*12/1000000 -> 1.9007658 | H6: =H4*1000*12/1000000 -> 1.9482849 | I6: =I4*1000*12/1000000 -> 1.9969921 | ... K6: =K4*1000*12/1000000 -> 2.0980898
A8: Capital Assumpetion
A9: Construction Cost per MW | B9: 2.8 | C9: 2.7 | D9: 2.6 | E9: 2.5 | F9: 2.4 | G9: 2.35 | H9: 2.3 | I9: 2.25 | J9: 2.2 | K9: 2.2 | L9: Capex = Incremental MW × Construction Cost per MW
A11: Financial Assumptions
A12: EBIT Margin | B12: -0.8 | C12: -0.3 | D12: 0.05 | E12: 0.15 | F12: 0.25 | G12: 0.28 | H12: 0.3 | I12: 0.31 | J12: 0.32 | K12: 0.32 | L12: Analyst assumption based on expected operating leverage
A13: Tax Rate | B13: 0 | C13: 0 | D13: 0.21 | E13: 0.21 | F13: 0.21 | G13: 0.21 | H13: 0.21 | I13: 0.21 | J13: 0.21 | K13: 0.21
A14: D&A (% Revenue) | B14: 0.05 | C14: 0.06 | D14: 0.07 | E14: 0.07 | F14: 0.07 | G14: 0.07 | H14: 0.07 | I14: 0.07 | J14: 0.07 | K14: 0.07 | L14: Analyst assumption
A15: NWC (% Revenue) | B15: 0.05 | C15: 0.05 | D15: 0.05 | E15: 0.05 | F15: 0.05 | G15: 0.05 | H15: 0.05 | I15: 0.05 | J15: 0.05 | K15: 0.05 | L15: Analyst assumption

Sheet Operating Forecast
A1: Item | B1: FY2026E | C1: FY2027E | D1: FY2028E | E1: FY2029E | F1: FY2030E | G1: FY2031E | H1: FY2032E | I1: FY2033E | J1: FY2034E | K1: FY2035E
A2: Revenue | B2: ='Operating Assumptions'!B2*'Operating Assumptions'!B3*'Operating Assumptions'!B6 -> 168 | C2: ='Operating Assumptions'!C2*'Operating Assumptions'!C3*'Operating Assumptions'!C6 -> 1937.25 | D2: ='Operating Assumptions'!D2*'Operating Assumptions'!D3*'Operating Assumptions'!D6 -> 3750.7312 | E2: ='Operating Assumptions'!E2*'Operating Assumptions'!E3*'Operating Assumptions'!E6 -> 5698.9052 | F2: ='Operating Assumptions'!F2*'Operating Assumptions'!F3*'Operating Assumptions'!F6 -> 7927.5842 | G2: ='Operating Assumptions'!G2*'Operating Assumptions'!G3*'Operating Assumptions'!G6 -> 9931.5013 | H2: ='Operating Assumptions'!H2*'Operating Assumptions'!H3*'Operating Assumptions'!H6 -> 12157.298 | I2: ='Operating Assumptions'!I2*'Operating Assumptions'!I3*'Operating Assumptions'!I6 -> 15336.899 | ... K2: ='Operating Assumptions'!K2*'Operating Assumptions'!K3*'Operating Assumptions'!K6 -> 20351.471
A3: Revenue Growth | B3: =IFERROR(B2/#REF!-1, "N/A") -> N/A | C3: N/M | D3: =D2/C2-1 -> 0.93611111 | E3: =E2/D2-1 -> 0.51941176 | F3: =F2/E2-1 -> 0.39107143 | G3: =G2/F2-1 -> 0.25277778 | H3: =H2/G2-1 -> 0.22411483 | I3: =I2/H2-1 -> 0.26153846 | J3: =J2/I2-1 -> 0.16513672 | K3: =K2/J2-1 -> 0.13888889
A4: EBIT Margin | B4: ='Operating Assumptions'!B12 -> -0.8 | C4: ='Operating Assumptions'!C12 -> -0.3 | D4: ='Operating Assumptions'!D12 -> 0.05 | E4: ='Operating Assumptions'!E12 -> 0.15 | F4: ='Operating Assumptions'!F12 -> 0.25 | G4: ='Operating Assumptions'!G12 -> 0.28 | H4: ='Operating Assumptions'!H12 -> 0.3 | I4: ='Operating Assumptions'!I12 -> 0.31 | ... K4: ='Operating Assumptions'!K12 -> 0.32
A5: EBIT | B5: =B2*B4 -> -134.4 | C5: =C2*C4 -> -581.175 | D5: =D2*D4 -> 187.53656 | E5: =E2*E4 -> 854.83578 | F5: =F2*F4 -> 1981.896 | G5: =G2*G4 -> 2780.8204 | H5: =H2*H4 -> 3647.1894 | I5: =I2*I4 -> 4754.4387 | ... K5: =K2*K4 -> 6512.4707
A6: Tax Rate | B6: ='Operating Assumptions'!B13 -> 0 | C6: ='Operating Assumptions'!C13 -> 0 | D6: ='Operating Assumptions'!D13 -> 0.21 | E6: ='Operating Assumptions'!E13 -> 0.21 | F6: ='Operating Assumptions'!F13 -> 0.21 | G6: ='Operating Assumptions'!G13 -> 0.21 | H6: ='Operating Assumptions'!H13 -> 0.21 | I6: ='Operating Assumptions'!I13 -> 0.21 | ... K6: ='Operating Assumptions'!K13 -> 0.21
A7: NOPAT | B7: =IF(B5>0,B5*(1-B6),B5) -> -134.4 | C7: =IF(C5>0,C5*(1-C6),C5) -> -581.175 | D7: =IF(D5>0,D5*(1-D6),D5) -> 148.15388 | E7: =IF(E5>0,E5*(1-E6),E5) -> 675.32026 | F7: =IF(F5>0,F5*(1-F6),F5) -> 1565.6979 | G7: =IF(G5>0,G5*(1-G6),G5) -> 2196.8481 | H7: =IF(H5>0,H5*(1-H6),H5) -> 2881.2796 | I7: =IF(I5>0,I5*(1-I6),I5) -> 3756.0066 | ... K7: =IF(K5>0,K5*(1-K6),K5) -> 5144.8519
A8: D&A | B8: =B2*'Operating Assumptions'!B14 -> 8.4 | C8: =C2*'Operating Assumptions'!C14 -> 116.235 | D8: =D2*'Operating Assumptions'!D14 -> 262.55119 | E8: =E2*'Operating Assumptions'!E14 -> 398.92336 | F8: =F2*'Operating Assumptions'!F14 -> 554.93089 | G8: =G2*'Operating Assumptions'!G14 -> 695.20509 | H8: =H2*'Operating Assumptions'!H14 -> 851.01086 | I8: =I2*'Operating Assumptions'!I14 -> 1073.5829 | ... K8: =K2*'Operating Assumptions'!K14 -> 1424.603
A9: Incremental MV | B9: ='Operating Assumptions'!B2-0 -> 200 | C9: ='Operating Assumptions'!C2-'Operating Assumptions'!B2 -> 1300 | D9: ='Operating Assumptions'!D2-'Operating Assumptions'!C2 -> 1000 | E9: ='Operating Assumptions'!E2-'Operating Assumptions'!D2 -> 1000 | F9: ='Operating Assumptions'!F2-'Operating Assumptions'!E2 -> 1000 | G9: ='Operating Assumptions'!G2-'Operating Assumptions'!F2 -> 1000 | H9: ='Operating Assumptions'!H2-'Operating Assumptions'!G2 -> 1000 | I9: ='Operating Assumptions'!I2-'Operating Assumptions'!H2 -> 1500 | J9: ='Operating Assumptions'!J2-'Operating Assumptions'!I2 -> 1000 | K9: ='Operating Assumptions'!K2-'Operating Assumptions'!J2 -> 1000
A10: Capex | B10: ='Operating Forecast'!B9*'Operating Assumptions'!B9 -> 560 | C10: ='Operating Forecast'!C9*'Operating Assumptions'!C9 -> 3510 | D10: ='Operating Forecast'!D9*'Operating Assumptions'!D9 -> 2600 | E10: ='Operating Forecast'!E9*'Operating Assumptions'!E9 -> 2500 | F10: ='Operating Forecast'!F9*'Operating Assumptions'!F9 -> 2400 | G10: ='Operating Forecast'!G9*'Operating Assumptions'!G9 -> 2350 | H10: ='Operating Forecast'!H9*'Operating Assumptions'!H9 -> 2300 | I10: ='Operating Forecast'!I9*'Operating Assumptions'!I9 -> 3375 | ... K10: ='Operating Forecast'!K9*'Operating Assumptions'!K9 -> 2200
A11: NWC (% Revenue) | B11: 0.05 | C11: 0.05 | D11: 0.05 | E11: 0.05 | F11: 0.05 | G11: 0.05 | H11: 0.05 | I11: 0.05 | J11: 0.05 | K11: 0.05
A12: NWC | B12: =B11*B2 -> 8.4 | C12: =C11*C2 -> 96.8625 | D12: =D11*D2 -> 187.53656 | E12: =E11*E2 -> 284.94526 | F12: =F11*F2 -> 396.37921 | G12: =G11*G2 -> 496.57506 | H12: =H11*H2 -> 607.8649 | I12: =I11*I2 -> 766.84495 | ... K12: =K11*K2 -> 1017.5735
A13: ΔNWC | B13: =B12-0 -> 8.4 | C13: =C12-B12 -> 88.4625 | D13: =D12-C12 -> 90.674062 | E13: =E12-D12 -> 97.408697 | F13: =F12-E12 -> 111.43395 | G13: =G12-F12 -> 100.19586 | H13: =H12-G12 -> 111.28984 | I13: =I12-H12 -> 158.98005 | J13: =J12-I12 -> 126.63426 | K13: =K12-J12 -> 124.09434
A14: FCF | B14: =B7+B8-B10-B13 -> -694.4 | C14: =C7+C8-C10-C13 -> -4063.4025 | D14: =D7+D8-D10-D13 -> -2279.969 | E14: =E7+E8-E10-E13 -> -1523.1651 | F14: =F7+F8-F10-F13 -> -390.80518 | G14: =G7+G8-G10-G13 -> 441.85732 | H14: =H7+H8-H10-H13 -> 1321.0007 | I14: =I7+I8-I10-I13 -> 1295.6095 | ... K14: =K7+K8-K10-K13 -> 4245.3605

Sheet WACC Assumptions
A1: WACC Assumptions | B1: Value | C1: Source
A2: Risk-free Rate | B2: 0.046 | C2: 10-Year U.S. Treasury Yield
A3: Equity Risk Premium | B3: 0.042 | C3: Damodaran (July 2026)
A4: Beta | B4: 1.6 | C4: Comparable AI/Data Center Infrastructure
A5: Cost of Equity | B5: =B2+B4*B3 -> 0.1132 | C5: risk free + beta*equity risk premium
A6: Pre-tax Cost of Debt | B6: 0.08 | C6: Development-stage infrastructure
A7: Tax Rate | B7: 0.21 | C7: Forecast
A8: After-tax Cost of Debt | B8: =B6*(1-B7) -> 0.0632
A9: Debt Weight | B9: 0.2
A10: Equity Weight | B10: =1-B9 -> 0.8
A11: WACC | B11: =B5*B10+B9*B8 -> 0.1032 | C11: Cost of equity×equity weight + Cost of Debt×debt weight

Sheet DCF & Sensitivity Analysis
A1: WACC& Terminal | B1: Value | S1: Sensitivity Analysis
A2: WACC | B2: 0.1032
A3: Terminal Growth | B3: =2.5% -> 0.025
A6: Item | B6: FY26E | C6: FY27E | D6: FY28E | E6: FY29E | F6: FY30E | G6: FY31E | H6: FY32E | I6: FY33E | J6: FY34E | K6: FY35E | L6: FY36E
A7: FCF | B7: ='Operating Forecast'!B14 -> -694.4 | C7: ='Operating Forecast'!C14 -> -4063.4025 | D7: ='Operating Forecast'!D14 -> -2279.969 | E7: ='Operating Forecast'!E14 -> -1523.1651 | F7: ='Operating Forecast'!F14 -> -390.80518 | G7: ='Operating Forecast'!G14 -> 441.85732 | H7: ='Operating Forecast'!H14 -> 1321.0007 | I7: ='Operating Forecast'!I14 -> 1295.6095 | ... K7: ='Operating Forecast'!K14 -> 4245.3605 | L7: =Table37[[#This Row],[FY35E]]*(1+B3) -> 4351.4945
A8: Discount Factor | B8: =1/(1+B2)^1 -> 0.90645395 | C8: =1/(1+$B$2)^2 -> 0.82165877 | D8: =1/(1+$B$2)^3 -> 0.74479584 | E8: =1/(1+$B$2)^4 -> 0.67512313 | F8: =1/(1+$B$2)^5 -> 0.61196803 | G8: =1/(1+$B$2)^6 -> 0.55472084 | H8: =1/(1+$B$2)^7 -> 0.5028289 | I8: =1/(1+$B$2)^8 -> 0.45579124 | J8: =1/(1+$B$2)^9 -> 0.41315377 | K8: =1/(1+$B$2)^10 -> 0.37450487
A9: PV of Discrete | B9: =B7*B8 -> -629.44162 | C9: =C7*C8 -> -3338.7303 | D9: =D7*D8 -> -1698.1114 | E9: =E7*E8 -> -1028.324 | F9: =F7*F8 -> -239.16028 | G9: =G7*G8 -> 245.10746 | H9: =H7*H8 -> 664.23731 | I9: =I7*I8 -> 590.52745 | ... K9: =K7*K8 -> 1589.9082
A10: Terminal Value | K10: =L7/(B2-B3) -> 55645.71
A11: PV of Terminal | K11: =K10/(1+B2)^10 -> 20839.589
A12: Total Cash Flow | B12: =B9+B11 -> -629.44162 | C12: =C9+C11 -> -3338.7303 | D12: =D9+D11 -> -1698.1114 | E12: =E9+E11 -> -1028.324 | F12: =F9+F11 -> -239.16028 | G12: =G9+G11 -> 245.10746 | H12: =H9+H11 -> 664.23731 | I12: =I9+I11 -> 590.52745 | ... K12: =K9+K11 -> 22429.497
A18: ENTERPRISE VALUE | G18: EQUITY VALUE | S18: ENTERPRISE VALUE | AB18: EQUITY VALUE PER SHARE
A19: PV of Discrete | B19: =SUM(B9:K9) -> -2422.0493 | C19: =B19/B21 -> -0.13150775 | G19: Enterprise Value | I19: =B21 -> 18417.54
A20: PV of Teminal | B20: =K11 -> 20839.589 | C20: =B20/B21 -> 1.1315078 | G20: Less: Net Debt | I20: ='Historical Data'!C23 -> 109.799
A21: Enterprise Value | B21: =SUM(B19:B20) -> 18417.54 | C21: =SUM(C19:C20) -> 1 | G21: Add: Cash | I21: ='Historical Data'!C16 -> 408.529 | S21: Terminal Growth Rate | AC21: Terminal Growth Rate
G22: Equity Value | I22: =I19-I20+I21 -> 18716.27 | P22: =$I$19 -> 18417.54 | Q22: 0.015 | R22: 0.02 | S22: 0.025 | T22: 0.03 | U22: 0.035 | AA22: 0.015 | AB22: 0.02 | AC22: 0.025 | AD22: 0.03 | AE22: 0.035
P23: 0.08 | Q23: 28821.649 | R23: 31544.389 | S23: 34762.172 | T23: 38623.513 | U23: 43342.929 | Z23: 0.08 | AA23: =Q38/$C$26 -> 46.234581 | AB23: =R38/$C$26 -> 50.55749 | AC23: =S38/$C$26 -> 55.666382 | AD23: =T38/$C$26 -> 61.797053 | AE23: =U38/$C$26 -> 69.290095
A24: EQUITY VALUE PER SHARE | G24: PREMIUM (DISCOUNT) | P24: 0.09 | Q24: 22132.637 | R24: 23994.239 | S24: 26142.241 | T24: 28648.243 | U24: 31609.882 | Z24: 0.09 | AA24: =Q39/$C$26 -> 35.614401 | AB24: =R39/$C$26 -> 38.570076 | AC24: =S39/$C$26 -> 41.980471 | AD24: =T39/$C$26 -> 45.959264 | AE24: =U39/$C$26 -> 50.661474
A25: Equity Value | C25: =I22 -> 18716.27 | G25: Intransic Value | H25: (USD/sh) | I25: =C27 -> 29.715922 | O25: WA | P25: 0.1032 | Q25: 15874.513 | R25: 17069.613 | S25: 18417.54 | T25: 19949.609 | U25: 21706.323 | Y25: WA | Z25: 0.1032 | AA25: =Q40/$C$26 -> 25.678344 | AB25: =R40/$C$26 -> 27.575812 | AC25: =S40/$C$26 -> 29.715922 | AD25: =T40/$C$26 -> 32.148397 | AE25: =U40/$C$26 -> 34.93754
A26: Shares Outstanding | C26: ='Historical Data'!C24 -> 629.83979 | G26: Current Price | H26: (USD/sh) | I26: =6.65 -> 6.65 | O26: CC | P26: 0.11 | Q26: 13423.879 | R26: 14394.415 | S26: 15479.132 | T26: 16699.438 | U26: 18082.452 | Y26: CC | Z26: 0.11 | AA26: =Q41/$C$26 -> 21.787459 | AB26: =R41/$C$26 -> 23.328385 | AC26: =S41/$C$26 -> 25.050595 | AD26: =T41/$C$26 -> 26.988082 | AE26: =U41/$C$26 -> 29.1839
A27: Intransic Value | B27: (USD/sh) | C27: =C25/C26 -> 29.715922 | G27: Premium(Discount) | I27: =(I25-I26)/I26 -> 3.4685597 | P27: 0.12 | Q27: 10494.064 | R27: 11223.074 | S27: 12028.821 | T27: 12924.096 | U27: 13924.697 | Z27: 0.12 | AA27: =Q42/$C$26 -> 17.135777 | AB27: =R42/$C$26 -> 18.293229 | AC27: =S42/$C$26 -> 19.572518 | AD27: =T42/$C$26 -> 20.993951 | AE27: =U42/$C$26 -> 22.58261
S33: EQUITY VALUE | AA33: PREMIUM(DISCOUNT) TO CURRENT PRICE
S36: Terminal Growth Rate | AC36: Terminal Growth Rate
Q37: 0.015 | R37: 0.02 | S37: 0.025 | T37: 0.03 | U37: 0.035 | AA37: 0.015 | AB37: 0.02 | AC37: 0.025 | AD37: 0.03 | AE37: 0.035
P38: 0.08 | Q38: =Q23-$I$20+$I$21 -> 29120.379 | R38: =R23-$I$20+$I$21 -> 31843.119 | S38: =S23-$I$20+$I$21 -> 35060.902 | T38: =T23-$I$20+$I$21 -> 38922.243 | U38: =U23-$I$20+$I$21 -> 43641.659 | Z38: 0.08 | AA38: =AA23/$I$26-1 -> 5.9525685 | AB38: =AB23/$I$26-1 -> 6.60263 | AC38: =AC23/$I$26-1 -> 7.3708845 | AD38: =AD23/$I$26-1 -> 8.2927899 | AE38: =AE23/$I$26-1 -> 9.4195631
P39: 0.09 | Q39: =Q24-$I$20+$I$21 -> 22431.367 | R39: =R24-$I$20+$I$21 -> 24292.969 | S39: =S24-$I$20+$I$21 -> 26440.971 | T39: =T24-$I$20+$I$21 -> 28946.973 | U39: =U24-$I$20+$I$21 -> 31908.612 | Z39: 0.09 | AA39: =AA24/$I$26-1 -> 4.355549 | AB39: =AB24/$I$26-1 -> 4.8000114 | AC39: =AC24/$I$26-1 -> 5.3128527 | AD39: =AD24/$I$26-1 -> 5.9111675 | AE39: =AE24/$I$26-1 -> 6.6182668
O40: WA | P40: 0.1032 | Q40: =Q25-$I$20+$I$21 -> 16173.243 | R40: =R25-$I$20+$I$21 -> 17368.343 | S40: =S25-$I$20+$I$21 -> 18716.27 | T40: =T25-$I$20+$I$21 -> 20248.339 | U40: =U25-$I$20+$I$21 -> 22005.053 | Y40: WA | Z40: 0.1032 | AA40: =AA25/$I$26-1 -> 2.8614052 | AB40: =AB25/$I$26-1 -> 3.1467386 | AC40: =AC25/$I$26-1 -> 3.4685597 | AD40: =AD25/$I$26-1 -> 3.8343454 | AE40: =AE25/$I$26-1 -> 4.2537653
O41: CC | P41: 0.11 | Q41: =Q26-$I$20+$I$21 -> 13722.609 | R41: =R26-$I$20+$I$21 -> 14693.145 | S41: =S26-$I$20+$I$21 -> 15777.862 | T41: =T26-$I$20+$I$21 -> 16998.168 | U41: =U26-$I$20+$I$21 -> 18381.182 | Y41: CC | Z41: 0.11 | AA41: =AA26/$I$26-1 -> 2.2763097 | AB41: =AB26/$I$26-1 -> 2.5080278 | AC41: =AC26/$I$26-1 -> 2.7670068 | AD41: =AD26/$I$26-1 -> 3.0583582 | AE41: =AE26/$I$26-1 -> 3.3885565
P42: 0.12 | Q42: =Q27-$I$20+$I$21 -> 10792.794 | R42: =R27-$I$20+$I$21 -> 11521.804 | S42: =S27-$I$20+$I$21 -> 12327.551 | T42: =T27-$I$20+$I$21 -> 13222.826 | U42: =U27-$I$20+$I$21 -> 14223.427 | Z42: 0.12 | AA42: =AA27/$I$26-1 -> 1.5768086 | AB42: =AB27/$I$26-1 -> 1.7508616 | AC42: =AC27/$I$26-1 -> 1.9432359 | AD42: =AD27/$I$26-1 -> 2.1569851 | AE42: =AE27/$I$26-1 -> 2.3958812
